jxh_env/__init__.py
jxh_env/envs/__init__.py
jxh_env/envs/env_jxh.py
jxh_env-0.0.1.dist-info/METADATA
jxh_env-0.0.1.dist-info/WHEEL
jxh_env-0.0.1.dist-info/top_level.txt
jxh_env-0.0.1.dist-info/RECORD
