Metadata-Version: 2.1
Name: jxh-env
Version: 0.0.1
Summary: A OpenAI Gym Env for jxh
Home-page: UNKNOWN
License: UNKNOWN
Platform: UNKNOWN
Requires-Dist: gym
